LICENSE
MANIFEST.in
README.rst
setup.py
django_mediautils.egg-info/PKG-INFO
django_mediautils.egg-info/SOURCES.txt
django_mediautils.egg-info/dependency_links.txt
django_mediautils.egg-info/not-zip-safe
django_mediautils.egg-info/requires.txt
django_mediautils.egg-info/top_level.txt
mediautils/__init__.py
mediautils/admin.py
mediautils/apps.py
mediautils/models.py
mediautils/tasks.py
mediautils/tests.py
mediautils/urls.py
mediautils/utils.py
mediautils/views.py
mediautils/migrations/__init__.py